{
  "headers": {
    "last-modified": "Wed, 22 Dec 2021 15:29:08 GMT",
    "server": "deploy/us-east4-c",
    "cache-control": "public, max-age=31536000, immutable",
    "content-length": "1982",
    "content-type": "application/typescript; charset=utf-8",
    "x-amz-id-2": "VN8IPm9RcXpIab1D1N1VtwVlX68bXLnF4ZCuUEhYvv4P5CNkRBTWA9XeERS4bKIlOIk+Hq5cGik=",
    "access-control-allow-origin": "*",
    "x-amz-request-id": "NH5KC7CH2H03J0Y1",
    "x-amz-version-id": "biT6apGgI.p0BitUeQcIs89Qapzjj.Tm",
    "etag": "\"c2c0a51099403711f5d728dbc7d1eb99\"",
    "date": "Thu, 23 Dec 2021 15:33:09 GMT"
  },
  "url": "https://deno.land/std@0.119.0/async/mux_async_iterator.ts",
  "now": {
    "secs_since_epoch": 1640273588,
    "nanos_since_epoch": 469091000
  }
}